{
	"type": "sandbox",
	"ns": "downthemall.net",
	"prefix": "imagefap.com",
	"match": "^http://.*imagefap\\.com/(?:image\\.php|photo/\\d+)",
	"resolve": "var lD = function (s) {\n  var s1 = unescape(s.substr(0, s.length - 1));\n  var t = \"\";\n  for (i = 0; i < s1.length; i++) {\n    t += String.fromCharCode(s1.charCodeAt(i) - s.substr(s.length - 1, 1));\n  }\n  return unescape(t);\n};\nfunction doit() {\n  var m = /id=\"mainPhoto\".+?src=\"(.+?)\"/.exec(responseText);\n  if (m && m.length >= 2) {\n    setURL(m[1]);\n    finish(); \n    return;\n  }\n  // old school\n  m = /lD\\('(.*?)'\\)/.exec(responseText);\n  if (m && m.length >= 2) {\n    setURL(lD(m[1]));\n    finish();\n    return;\n  }\n  if (/The image you are trying to access does not exist/.test(responseText)) {\n    markGone(404, 'The image you are trying to access does not exist');\n  }\n  // nothing else helps :p\n  finish();\n}\ndoit();",
	"static": true
}